aomie/__init__.py
aomie/__main__.py
aomie/cli.py
aomie/handling.py
aomie-0.0.0.dist-info/AUTHORS.rst
aomie-0.0.0.dist-info/LICENSE
aomie-0.0.0.dist-info/METADATA
aomie-0.0.0.dist-info/WHEEL
aomie-0.0.0.dist-info/entry_points.txt
aomie-0.0.0.dist-info/top_level.txt
aomie-0.0.0.dist-info/RECORD
