Metadata-Version: 2.1
Name: aomie
Version: 0.0.0
Summary: Pure Python 3 open source library to handle Iberian electricity market data published by OMIE.
Home-page: https://github.com/qheuristics/aomie
Author: Guillermo Lozano Branger
Author-email: qheuristics@gmail.com
License: MIT
Project-URL: Documentation, https://aomie.readthedocs.io/
Project-URL: Changelog, https://aomie.readthedocs.io/en/latest/changelog.html
Project-URL: Issue Tracker, https://github.com/qheuristics/aomie/issues
Keywords: OMIE,electricity market,data handling
Platform: UNKNOWN
Classifier: Development Status :: 3 - Alpha
Classifier: Intended Audience :: Developers
Classifier: License :: OSI Approved :: MIT License
Classifier: Operating System :: Unix
Classifier: Operating System :: POSIX
Classifier: Operating System :: Microsoft :: Windows
Classifier: Programming Language :: Python
Classifier: Programming Language :: Python :: 3.7
Classifier: Programming Language :: Python :: Implementation :: CPython
Classifier: Topic :: Scientific/Engineering :: Information Analysis
Requires-Python: >=3.6
Requires-Dist: click
Requires-Dist: toml
Requires-Dist: pandas
